thin_ws_server/__init__.py
thin_ws_server/websocket_server.py
thin_ws_server-1.0.3.dist-info/LICENSE
thin_ws_server-1.0.3.dist-info/METADATA
thin_ws_server-1.0.3.dist-info/WHEEL
thin_ws_server-1.0.3.dist-info/top_level.txt
thin_ws_server-1.0.3.dist-info/RECORD
