Metadata-Version: 2.1
Name: thin-ws-server
Version: 1.0.3
Summary: small implementation of websocket server.
Home-page: https://github.com/atoy322/ws_server
Author: atoy322
License: UNKNOWN
Platform: UNKNOWN
License-File: LICENSE
